supervisor_alert.py
supervisor_alert-0.6.2.dist-info/DESCRIPTION.rst
supervisor_alert-0.6.2.dist-info/METADATA
supervisor_alert-0.6.2.dist-info/RECORD
supervisor_alert-0.6.2.dist-info/WHEEL
supervisor_alert-0.6.2.dist-info/entry_points.txt
supervisor_alert-0.6.2.dist-info/metadata.json
supervisor_alert-0.6.2.dist-info/top_level.txt
