Metadata-Version: 2.0
Name: supervisor-alert
Version: 0.6.2
Summary: Receive notifications for Supervisor process events.
Home-page: https://github.com/rahiel/supervisor-alert
Author: Rahiel Kasim
Author-email: rahielkasim@gmail.com
License: Apache-2.0
Keywords: supervisor alert event listener notify
Platform: UNKNOWN
Classifier: Development Status :: 4 - Beta
Classifier: Environment :: Console
Classifier: Intended Audience :: Developers
Classifier: Intended Audience :: System Administrators
Classifier: License :: OSI Approved :: Apache Software License
Classifier: Operating System :: POSIX
Classifier: Programming Language :: Python :: 2.7
Classifier: Topic :: System :: Monitoring
Classifier: Topic :: System :: Systems Administration
